interface  org.apache.harmony.luni.internal.reflect.ProxyConstants extends java.lang.Object
{
    public static final int AccFinal;
    public static final int AccPrivate;
    public static final int AccProtected;
    public static final int AccPublic;
    public static final int AccStatic;
    public static final int AccSuper;
    public static final int ClassTag;
    public static final char[] CodeName;
    public static final int DoubleTag;
    public static final char[] ExceptionsName;
    public static final int FieldRefTag;
    public static final int FloatTag;
    public static final char[] Init;
    public static final int IntegerTag;
    public static final int InterfaceMethodRefTag;
    public static final int LongTag;
    public static final int MethodRefTag;
    public static final int NameAndTypeTag;
    public static final int OPC_aaload;
    public static final int OPC_aastore;
    public static final int OPC_aconst_null;
    public static final int OPC_aload;
    public static final int OPC_aload_0;
    public static final int OPC_aload_1;
    public static final int OPC_aload_2;
    public static final int OPC_aload_3;
    public static final int OPC_anewarray;
    public static final int OPC_areturn;
    public static final int OPC_arraylength;
    public static final int OPC_astore;
    public static final int OPC_astore_0;
    public static final int OPC_astore_1;
    public static final int OPC_astore_2;
    public static final int OPC_astore_3;
    public static final int OPC_athrow;
    public static final int OPC_baload;
    public static final int OPC_bastore;
    public static final int OPC_bipush;
    public static final int OPC_caload;
    public static final int OPC_castore;
    public static final int OPC_checkcast;
    public static final int OPC_d2f;
    public static final int OPC_d2i;
    public static final int OPC_d2l;
    public static final int OPC_dadd;
    public static final int OPC_daload;
    public static final int OPC_dastore;
    public static final int OPC_dcmpg;
    public static final int OPC_dcmpl;
    public static final int OPC_dconst_0;
    public static final int OPC_dconst_1;
    public static final int OPC_ddiv;
    public static final int OPC_dload;
    public static final int OPC_dload_0;
    public static final int OPC_dload_1;
    public static final int OPC_dload_2;
    public static final int OPC_dload_3;
    public static final int OPC_dmul;
    public static final int OPC_dneg;
    public static final int OPC_drem;
    public static final int OPC_dreturn;
    public static final int OPC_dstore;
    public static final int OPC_dstore_0;
    public static final int OPC_dstore_1;
    public static final int OPC_dstore_2;
    public static final int OPC_dstore_3;
    public static final int OPC_dsub;
    public static final int OPC_dup;
    public static final int OPC_dup2;
    public static final int OPC_dup2_x1;
    public static final int OPC_dup2_x2;
    public static final int OPC_dup_x1;
    public static final int OPC_dup_x2;
    public static final int OPC_f2d;
    public static final int OPC_f2i;
    public static final int OPC_f2l;
    public static final int OPC_fadd;
    public static final int OPC_faload;
    public static final int OPC_fastore;
    public static final int OPC_fcmpg;
    public static final int OPC_fcmpl;
    public static final int OPC_fconst_0;
    public static final int OPC_fconst_1;
    public static final int OPC_fconst_2;
    public static final int OPC_fdiv;
    public static final int OPC_fload;
    public static final int OPC_fload_0;
    public static final int OPC_fload_1;
    public static final int OPC_fload_2;
    public static final int OPC_fload_3;
    public static final int OPC_fmul;
    public static final int OPC_fneg;
    public static final int OPC_frem;
    public static final int OPC_freturn;
    public static final int OPC_fstore;
    public static final int OPC_fstore_0;
    public static final int OPC_fstore_1;
    public static final int OPC_fstore_2;
    public static final int OPC_fstore_3;
    public static final int OPC_fsub;
    public static final int OPC_getfield;
    public static final int OPC_getstatic;
    public static final int OPC_goto;
    public static final int OPC_goto_w;
    public static final int OPC_i2b;
    public static final int OPC_i2c;
    public static final int OPC_i2d;
    public static final int OPC_i2f;
    public static final int OPC_i2l;
    public static final int OPC_i2s;
    public static final int OPC_iadd;
    public static final int OPC_iaload;
    public static final int OPC_iand;
    public static final int OPC_iastore;
    public static final int OPC_iconst_0;
    public static final int OPC_iconst_1;
    public static final int OPC_iconst_2;
    public static final int OPC_iconst_3;
    public static final int OPC_iconst_4;
    public static final int OPC_iconst_5;
    public static final int OPC_iconst_m1;
    public static final int OPC_idiv;
    public static final int OPC_if_acmpeq;
    public static final int OPC_if_acmpne;
    public static final int OPC_if_icmpeq;
    public static final int OPC_if_icmpge;
    public static final int OPC_if_icmpgt;
    public static final int OPC_if_icmple;
    public static final int OPC_if_icmplt;
    public static final int OPC_if_icmpne;
    public static final int OPC_ifeq;
    public static final int OPC_ifge;
    public static final int OPC_ifgt;
    public static final int OPC_ifle;
    public static final int OPC_iflt;
    public static final int OPC_ifne;
    public static final int OPC_ifnonnull;
    public static final int OPC_ifnull;
    public static final int OPC_iinc;
    public static final int OPC_iload;
    public static final int OPC_iload_0;
    public static final int OPC_iload_1;
    public static final int OPC_iload_2;
    public static final int OPC_iload_3;
    public static final int OPC_imul;
    public static final int OPC_ineg;
    public static final int OPC_instanceof;
    public static final int OPC_invokeinterface;
    public static final int OPC_invokespecial;
    public static final int OPC_invokestatic;
    public static final int OPC_invokevirtual;
    public static final int OPC_ior;
    public static final int OPC_irem;
    public static final int OPC_ireturn;
    public static final int OPC_ishl;
    public static final int OPC_ishr;
    public static final int OPC_istore;
    public static final int OPC_istore_0;
    public static final int OPC_istore_1;
    public static final int OPC_istore_2;
    public static final int OPC_istore_3;
    public static final int OPC_isub;
    public static final int OPC_iushr;
    public static final int OPC_ixor;
    public static final int OPC_jsr;
    public static final int OPC_jsr_w;
    public static final int OPC_l2d;
    public static final int OPC_l2f;
    public static final int OPC_l2i;
    public static final int OPC_ladd;
    public static final int OPC_laload;
    public static final int OPC_land;
    public static final int OPC_lastore;
    public static final int OPC_lcmp;
    public static final int OPC_lconst_0;
    public static final int OPC_lconst_1;
    public static final int OPC_ldc;
    public static final int OPC_ldc2_w;
    public static final int OPC_ldc_w;
    public static final int OPC_ldiv;
    public static final int OPC_lload;
    public static final int OPC_lload_0;
    public static final int OPC_lload_1;
    public static final int OPC_lload_2;
    public static final int OPC_lload_3;
    public static final int OPC_lmul;
    public static final int OPC_lneg;
    public static final int OPC_lookupswitch;
    public static final int OPC_lor;
    public static final int OPC_lrem;
    public static final int OPC_lreturn;
    public static final int OPC_lshl;
    public static final int OPC_lshr;
    public static final int OPC_lstore;
    public static final int OPC_lstore_0;
    public static final int OPC_lstore_1;
    public static final int OPC_lstore_2;
    public static final int OPC_lstore_3;
    public static final int OPC_lsub;
    public static final int OPC_lushr;
    public static final int OPC_lxor;
    public static final int OPC_monitorenter;
    public static final int OPC_monitorexit;
    public static final int OPC_multianewarray;
    public static final int OPC_new;
    public static final int OPC_newarray;
    public static final int OPC_nop;
    public static final int OPC_pop;
    public static final int OPC_pop2;
    public static final int OPC_putfield;
    public static final int OPC_putstatic;
    public static final int OPC_ret;
    public static final int OPC_return;
    public static final int OPC_saload;
    public static final int OPC_sastore;
    public static final int OPC_sipush;
    public static final int OPC_swap;
    public static final int OPC_tableswitch;
    public static final int OPC_wide;
    public static final int StringTag;
    public static final int Utf8Tag;

    static void <clinit>()
    {
        char[] $r0;

        <org.apache.harmony.luni.internal.reflect.ProxyConstants: int Utf8Tag> = 1;

        <org.apache.harmony.luni.internal.reflect.ProxyConstants: int StringTag> = 8;

        <org.apache.harmony.luni.internal.reflect.ProxyConstants: int OPC_wide> = 196;

        <org.apache.harmony.luni.internal.reflect.ProxyConstants: int OPC_tableswitch> = 170;

        <org.apache.harmony.luni.internal.reflect.ProxyConstants: int OPC_swap> = 95;

        <org.apache.harmony.luni.internal.reflect.ProxyConstants: int OPC_sipush> = 17;

        <org.apache.harmony.luni.internal.reflect.ProxyConstants: int OPC_sastore> = 86;

        <org.apache.harmony.luni.internal.reflect.ProxyConstants: int OPC_saload> = 53;

        <org.apache.harmony.luni.internal.reflect.ProxyConstants: int OPC_return> = 177;

        <org.apache.harmony.luni.internal.reflect.ProxyConstants: int OPC_ret> = 169;

        <org.apache.harmony.luni.internal.reflect.ProxyConstants: int OPC_putstatic> = 179;

        <org.apache.harmony.luni.internal.reflect.ProxyConstants: int OPC_putfield> = 181;

        <org.apache.harmony.luni.internal.reflect.ProxyConstants: int OPC_pop2> = 88;

        <org.apache.harmony.luni.internal.reflect.ProxyConstants: int OPC_pop> = 87;

        <org.apache.harmony.luni.internal.reflect.ProxyConstants: int OPC_nop> = 0;

        <org.apache.harmony.luni.internal.reflect.ProxyConstants: int OPC_newarray> = 188;

        <org.apache.harmony.luni.internal.reflect.ProxyConstants: int OPC_new> = 187;

        <org.apache.harmony.luni.internal.reflect.ProxyConstants: int OPC_multianewarray> = 197;

        <org.apache.harmony.luni.internal.reflect.ProxyConstants: int OPC_monitorexit> = 195;

        <org.apache.harmony.luni.internal.reflect.ProxyConstants: int OPC_monitorenter> = 194;

        <org.apache.harmony.luni.internal.reflect.ProxyConstants: int OPC_lxor> = 131;

        <org.apache.harmony.luni.internal.reflect.ProxyConstants: int OPC_lushr> = 125;

        <org.apache.harmony.luni.internal.reflect.ProxyConstants: int OPC_lsub> = 101;

        <org.apache.harmony.luni.internal.reflect.ProxyConstants: int OPC_lstore_3> = 66;

        <org.apache.harmony.luni.internal.reflect.ProxyConstants: int OPC_lstore_2> = 65;

        <org.apache.harmony.luni.internal.reflect.ProxyConstants: int OPC_lstore_1> = 64;

        <org.apache.harmony.luni.internal.reflect.ProxyConstants: int OPC_lstore_0> = 63;

        <org.apache.harmony.luni.internal.reflect.ProxyConstants: int OPC_lstore> = 55;

        <org.apache.harmony.luni.internal.reflect.ProxyConstants: int OPC_lshr> = 123;

        <org.apache.harmony.luni.internal.reflect.ProxyConstants: int OPC_lshl> = 121;

        <org.apache.harmony.luni.internal.reflect.ProxyConstants: int OPC_lreturn> = 173;

        <org.apache.harmony.luni.internal.reflect.ProxyConstants: int OPC_lrem> = 113;

        <org.apache.harmony.luni.internal.reflect.ProxyConstants: int OPC_lor> = 129;

        <org.apache.harmony.luni.internal.reflect.ProxyConstants: int OPC_lookupswitch> = 171;

        <org.apache.harmony.luni.internal.reflect.ProxyConstants: int OPC_lneg> = 117;

        <org.apache.harmony.luni.internal.reflect.ProxyConstants: int OPC_lmul> = 105;

        <org.apache.harmony.luni.internal.reflect.ProxyConstants: int OPC_lload_3> = 33;

        <org.apache.harmony.luni.internal.reflect.ProxyConstants: int OPC_lload_2> = 32;

        <org.apache.harmony.luni.internal.reflect.ProxyConstants: int OPC_lload_1> = 31;

        <org.apache.harmony.luni.internal.reflect.ProxyConstants: int OPC_lload_0> = 30;

        <org.apache.harmony.luni.internal.reflect.ProxyConstants: int OPC_lload> = 22;

        <org.apache.harmony.luni.internal.reflect.ProxyConstants: int OPC_ldiv> = 109;

        <org.apache.harmony.luni.internal.reflect.ProxyConstants: int OPC_ldc_w> = 19;

        <org.apache.harmony.luni.internal.reflect.ProxyConstants: int OPC_ldc2_w> = 20;

        <org.apache.harmony.luni.internal.reflect.ProxyConstants: int OPC_ldc> = 18;

        <org.apache.harmony.luni.internal.reflect.ProxyConstants: int OPC_lconst_1> = 10;

        <org.apache.harmony.luni.internal.reflect.ProxyConstants: int OPC_lconst_0> = 9;

        <org.apache.harmony.luni.internal.reflect.ProxyConstants: int OPC_lcmp> = 148;

        <org.apache.harmony.luni.internal.reflect.ProxyConstants: int OPC_lastore> = 80;

        <org.apache.harmony.luni.internal.reflect.ProxyConstants: int OPC_land> = 127;

        <org.apache.harmony.luni.internal.reflect.ProxyConstants: int OPC_laload> = 47;

        <org.apache.harmony.luni.internal.reflect.ProxyConstants: int OPC_ladd> = 97;

        <org.apache.harmony.luni.internal.reflect.ProxyConstants: int OPC_l2i> = 136;

        <org.apache.harmony.luni.internal.reflect.ProxyConstants: int OPC_l2f> = 137;

        <org.apache.harmony.luni.internal.reflect.ProxyConstants: int OPC_l2d> = 138;

        <org.apache.harmony.luni.internal.reflect.ProxyConstants: int OPC_jsr_w> = 201;

        <org.apache.harmony.luni.internal.reflect.ProxyConstants: int OPC_jsr> = 168;

        <org.apache.harmony.luni.internal.reflect.ProxyConstants: int OPC_ixor> = 130;

        <org.apache.harmony.luni.internal.reflect.ProxyConstants: int OPC_iushr> = 124;

        <org.apache.harmony.luni.internal.reflect.ProxyConstants: int OPC_isub> = 100;

        <org.apache.harmony.luni.internal.reflect.ProxyConstants: int OPC_istore_3> = 62;

        <org.apache.harmony.luni.internal.reflect.ProxyConstants: int OPC_istore_2> = 61;

        <org.apache.harmony.luni.internal.reflect.ProxyConstants: int OPC_istore_1> = 60;

        <org.apache.harmony.luni.internal.reflect.ProxyConstants: int OPC_istore_0> = 59;

        <org.apache.harmony.luni.internal.reflect.ProxyConstants: int OPC_istore> = 54;

        <org.apache.harmony.luni.internal.reflect.ProxyConstants: int OPC_ishr> = 122;

        <org.apache.harmony.luni.internal.reflect.ProxyConstants: int OPC_ishl> = 120;

        <org.apache.harmony.luni.internal.reflect.ProxyConstants: int OPC_ireturn> = 172;

        <org.apache.harmony.luni.internal.reflect.ProxyConstants: int OPC_irem> = 112;

        <org.apache.harmony.luni.internal.reflect.ProxyConstants: int OPC_ior> = 128;

        <org.apache.harmony.luni.internal.reflect.ProxyConstants: int OPC_invokevirtual> = 182;

        <org.apache.harmony.luni.internal.reflect.ProxyConstants: int OPC_invokestatic> = 184;

        <org.apache.harmony.luni.internal.reflect.ProxyConstants: int OPC_invokespecial> = 183;

        <org.apache.harmony.luni.internal.reflect.ProxyConstants: int OPC_invokeinterface> = 185;

        <org.apache.harmony.luni.internal.reflect.ProxyConstants: int OPC_instanceof> = 193;

        <org.apache.harmony.luni.internal.reflect.ProxyConstants: int OPC_ineg> = 116;

        <org.apache.harmony.luni.internal.reflect.ProxyConstants: int OPC_imul> = 104;

        <org.apache.harmony.luni.internal.reflect.ProxyConstants: int OPC_iload_3> = 29;

        <org.apache.harmony.luni.internal.reflect.ProxyConstants: int OPC_iload_2> = 28;

        <org.apache.harmony.luni.internal.reflect.ProxyConstants: int OPC_iload_1> = 27;

        <org.apache.harmony.luni.internal.reflect.ProxyConstants: int OPC_iload_0> = 26;

        <org.apache.harmony.luni.internal.reflect.ProxyConstants: int OPC_iload> = 21;

        <org.apache.harmony.luni.internal.reflect.ProxyConstants: int OPC_iinc> = 132;

        <org.apache.harmony.luni.internal.reflect.ProxyConstants: int OPC_ifnull> = 198;

        <org.apache.harmony.luni.internal.reflect.ProxyConstants: int OPC_ifnonnull> = 199;

        <org.apache.harmony.luni.internal.reflect.ProxyConstants: int OPC_ifne> = 154;

        <org.apache.harmony.luni.internal.reflect.ProxyConstants: int OPC_iflt> = 155;

        <org.apache.harmony.luni.internal.reflect.ProxyConstants: int OPC_ifle> = 158;

        <org.apache.harmony.luni.internal.reflect.ProxyConstants: int OPC_ifgt> = 157;

        <org.apache.harmony.luni.internal.reflect.ProxyConstants: int OPC_ifge> = 156;

        <org.apache.harmony.luni.internal.reflect.ProxyConstants: int OPC_ifeq> = 153;

        <org.apache.harmony.luni.internal.reflect.ProxyConstants: int OPC_if_icmpne> = 160;

        <org.apache.harmony.luni.internal.reflect.ProxyConstants: int OPC_if_icmplt> = 161;

        <org.apache.harmony.luni.internal.reflect.ProxyConstants: int OPC_if_icmple> = 164;

        <org.apache.harmony.luni.internal.reflect.ProxyConstants: int OPC_if_icmpgt> = 163;

        <org.apache.harmony.luni.internal.reflect.ProxyConstants: int OPC_if_icmpge> = 162;

        <org.apache.harmony.luni.internal.reflect.ProxyConstants: int OPC_if_icmpeq> = 159;

        <org.apache.harmony.luni.internal.reflect.ProxyConstants: int OPC_if_acmpne> = 166;

        <org.apache.harmony.luni.internal.reflect.ProxyConstants: int OPC_if_acmpeq> = 165;

        <org.apache.harmony.luni.internal.reflect.ProxyConstants: int OPC_idiv> = 108;

        <org.apache.harmony.luni.internal.reflect.ProxyConstants: int OPC_iconst_m1> = 2;

        <org.apache.harmony.luni.internal.reflect.ProxyConstants: int OPC_iconst_5> = 8;

        <org.apache.harmony.luni.internal.reflect.ProxyConstants: int OPC_iconst_4> = 7;

        <org.apache.harmony.luni.internal.reflect.ProxyConstants: int OPC_iconst_3> = 6;

        <org.apache.harmony.luni.internal.reflect.ProxyConstants: int OPC_iconst_2> = 5;

        <org.apache.harmony.luni.internal.reflect.ProxyConstants: int OPC_iconst_1> = 4;

        <org.apache.harmony.luni.internal.reflect.ProxyConstants: int OPC_iconst_0> = 3;

        <org.apache.harmony.luni.internal.reflect.ProxyConstants: int OPC_iastore> = 79;

        <org.apache.harmony.luni.internal.reflect.ProxyConstants: int OPC_iand> = 126;

        <org.apache.harmony.luni.internal.reflect.ProxyConstants: int OPC_iaload> = 46;

        <org.apache.harmony.luni.internal.reflect.ProxyConstants: int OPC_iadd> = 96;

        <org.apache.harmony.luni.internal.reflect.ProxyConstants: int OPC_i2s> = 147;

        <org.apache.harmony.luni.internal.reflect.ProxyConstants: int OPC_i2l> = 133;

        <org.apache.harmony.luni.internal.reflect.ProxyConstants: int OPC_i2f> = 134;

        <org.apache.harmony.luni.internal.reflect.ProxyConstants: int OPC_i2d> = 135;

        <org.apache.harmony.luni.internal.reflect.ProxyConstants: int OPC_i2c> = 146;

        <org.apache.harmony.luni.internal.reflect.ProxyConstants: int OPC_i2b> = 145;

        <org.apache.harmony.luni.internal.reflect.ProxyConstants: int OPC_goto_w> = 200;

        <org.apache.harmony.luni.internal.reflect.ProxyConstants: int OPC_goto> = 167;

        <org.apache.harmony.luni.internal.reflect.ProxyConstants: int OPC_getstatic> = 178;

        <org.apache.harmony.luni.internal.reflect.ProxyConstants: int OPC_getfield> = 180;

        <org.apache.harmony.luni.internal.reflect.ProxyConstants: int OPC_fsub> = 102;

        <org.apache.harmony.luni.internal.reflect.ProxyConstants: int OPC_fstore_3> = 70;

        <org.apache.harmony.luni.internal.reflect.ProxyConstants: int OPC_fstore_2> = 69;

        <org.apache.harmony.luni.internal.reflect.ProxyConstants: int OPC_fstore_1> = 68;

        <org.apache.harmony.luni.internal.reflect.ProxyConstants: int OPC_fstore_0> = 67;

        <org.apache.harmony.luni.internal.reflect.ProxyConstants: int OPC_fstore> = 56;

        <org.apache.harmony.luni.internal.reflect.ProxyConstants: int OPC_freturn> = 174;

        <org.apache.harmony.luni.internal.reflect.ProxyConstants: int OPC_frem> = 114;

        <org.apache.harmony.luni.internal.reflect.ProxyConstants: int OPC_fneg> = 118;

        <org.apache.harmony.luni.internal.reflect.ProxyConstants: int OPC_fmul> = 106;

        <org.apache.harmony.luni.internal.reflect.ProxyConstants: int OPC_fload_3> = 37;

        <org.apache.harmony.luni.internal.reflect.ProxyConstants: int OPC_fload_2> = 36;

        <org.apache.harmony.luni.internal.reflect.ProxyConstants: int OPC_fload_1> = 35;

        <org.apache.harmony.luni.internal.reflect.ProxyConstants: int OPC_fload_0> = 34;

        <org.apache.harmony.luni.internal.reflect.ProxyConstants: int OPC_fload> = 23;

        <org.apache.harmony.luni.internal.reflect.ProxyConstants: int OPC_fdiv> = 110;

        <org.apache.harmony.luni.internal.reflect.ProxyConstants: int OPC_fconst_2> = 13;

        <org.apache.harmony.luni.internal.reflect.ProxyConstants: int OPC_fconst_1> = 12;

        <org.apache.harmony.luni.internal.reflect.ProxyConstants: int OPC_fconst_0> = 11;

        <org.apache.harmony.luni.internal.reflect.ProxyConstants: int OPC_fcmpl> = 149;

        <org.apache.harmony.luni.internal.reflect.ProxyConstants: int OPC_fcmpg> = 150;

        <org.apache.harmony.luni.internal.reflect.ProxyConstants: int OPC_fastore> = 81;

        <org.apache.harmony.luni.internal.reflect.ProxyConstants: int OPC_faload> = 48;

        <org.apache.harmony.luni.internal.reflect.ProxyConstants: int OPC_fadd> = 98;

        <org.apache.harmony.luni.internal.reflect.ProxyConstants: int OPC_f2l> = 140;

        <org.apache.harmony.luni.internal.reflect.ProxyConstants: int OPC_f2i> = 139;

        <org.apache.harmony.luni.internal.reflect.ProxyConstants: int OPC_f2d> = 141;

        <org.apache.harmony.luni.internal.reflect.ProxyConstants: int OPC_dup_x2> = 91;

        <org.apache.harmony.luni.internal.reflect.ProxyConstants: int OPC_dup_x1> = 90;

        <org.apache.harmony.luni.internal.reflect.ProxyConstants: int OPC_dup2_x2> = 94;

        <org.apache.harmony.luni.internal.reflect.ProxyConstants: int OPC_dup2_x1> = 93;

        <org.apache.harmony.luni.internal.reflect.ProxyConstants: int OPC_dup2> = 92;

        <org.apache.harmony.luni.internal.reflect.ProxyConstants: int OPC_dup> = 89;

        <org.apache.harmony.luni.internal.reflect.ProxyConstants: int OPC_dsub> = 103;

        <org.apache.harmony.luni.internal.reflect.ProxyConstants: int OPC_dstore_3> = 74;

        <org.apache.harmony.luni.internal.reflect.ProxyConstants: int OPC_dstore_2> = 73;

        <org.apache.harmony.luni.internal.reflect.ProxyConstants: int OPC_dstore_1> = 72;

        <org.apache.harmony.luni.internal.reflect.ProxyConstants: int OPC_dstore_0> = 71;

        <org.apache.harmony.luni.internal.reflect.ProxyConstants: int OPC_dstore> = 57;

        <org.apache.harmony.luni.internal.reflect.ProxyConstants: int OPC_dreturn> = 175;

        <org.apache.harmony.luni.internal.reflect.ProxyConstants: int OPC_drem> = 115;

        <org.apache.harmony.luni.internal.reflect.ProxyConstants: int OPC_dneg> = 119;

        <org.apache.harmony.luni.internal.reflect.ProxyConstants: int OPC_dmul> = 107;

        <org.apache.harmony.luni.internal.reflect.ProxyConstants: int OPC_dload_3> = 41;

        <org.apache.harmony.luni.internal.reflect.ProxyConstants: int OPC_dload_2> = 40;

        <org.apache.harmony.luni.internal.reflect.ProxyConstants: int OPC_dload_1> = 39;

        <org.apache.harmony.luni.internal.reflect.ProxyConstants: int OPC_dload_0> = 38;

        <org.apache.harmony.luni.internal.reflect.ProxyConstants: int OPC_dload> = 24;

        <org.apache.harmony.luni.internal.reflect.ProxyConstants: int OPC_ddiv> = 111;

        <org.apache.harmony.luni.internal.reflect.ProxyConstants: int OPC_dconst_1> = 15;

        <org.apache.harmony.luni.internal.reflect.ProxyConstants: int OPC_dconst_0> = 14;

        <org.apache.harmony.luni.internal.reflect.ProxyConstants: int OPC_dcmpl> = 151;

        <org.apache.harmony.luni.internal.reflect.ProxyConstants: int OPC_dcmpg> = 152;

        <org.apache.harmony.luni.internal.reflect.ProxyConstants: int OPC_dastore> = 82;

        <org.apache.harmony.luni.internal.reflect.ProxyConstants: int OPC_daload> = 49;

        <org.apache.harmony.luni.internal.reflect.ProxyConstants: int OPC_dadd> = 99;

        <org.apache.harmony.luni.internal.reflect.ProxyConstants: int OPC_d2l> = 143;

        <org.apache.harmony.luni.internal.reflect.ProxyConstants: int OPC_d2i> = 142;

        <org.apache.harmony.luni.internal.reflect.ProxyConstants: int OPC_d2f> = 144;

        <org.apache.harmony.luni.internal.reflect.ProxyConstants: int OPC_checkcast> = 192;

        <org.apache.harmony.luni.internal.reflect.ProxyConstants: int OPC_castore> = 85;

        <org.apache.harmony.luni.internal.reflect.ProxyConstants: int OPC_caload> = 52;

        <org.apache.harmony.luni.internal.reflect.ProxyConstants: int OPC_bipush> = 16;

        <org.apache.harmony.luni.internal.reflect.ProxyConstants: int OPC_bastore> = 84;

        <org.apache.harmony.luni.internal.reflect.ProxyConstants: int OPC_baload> = 51;

        <org.apache.harmony.luni.internal.reflect.ProxyConstants: int OPC_athrow> = 191;

        <org.apache.harmony.luni.internal.reflect.ProxyConstants: int OPC_astore_3> = 78;

        <org.apache.harmony.luni.internal.reflect.ProxyConstants: int OPC_astore_2> = 77;

        <org.apache.harmony.luni.internal.reflect.ProxyConstants: int OPC_astore_1> = 76;

        <org.apache.harmony.luni.internal.reflect.ProxyConstants: int OPC_astore_0> = 75;

        <org.apache.harmony.luni.internal.reflect.ProxyConstants: int OPC_astore> = 58;

        <org.apache.harmony.luni.internal.reflect.ProxyConstants: int OPC_arraylength> = 190;

        <org.apache.harmony.luni.internal.reflect.ProxyConstants: int OPC_areturn> = 176;

        <org.apache.harmony.luni.internal.reflect.ProxyConstants: int OPC_anewarray> = 189;

        <org.apache.harmony.luni.internal.reflect.ProxyConstants: int OPC_aload_3> = 45;

        <org.apache.harmony.luni.internal.reflect.ProxyConstants: int OPC_aload_2> = 44;

        <org.apache.harmony.luni.internal.reflect.ProxyConstants: int OPC_aload_1> = 43;

        <org.apache.harmony.luni.internal.reflect.ProxyConstants: int OPC_aload_0> = 42;

        <org.apache.harmony.luni.internal.reflect.ProxyConstants: int OPC_aload> = 25;

        <org.apache.harmony.luni.internal.reflect.ProxyConstants: int OPC_aconst_null> = 1;

        <org.apache.harmony.luni.internal.reflect.ProxyConstants: int OPC_aastore> = 83;

        <org.apache.harmony.luni.internal.reflect.ProxyConstants: int OPC_aaload> = 50;

        <org.apache.harmony.luni.internal.reflect.ProxyConstants: int NameAndTypeTag> = 12;

        <org.apache.harmony.luni.internal.reflect.ProxyConstants: int MethodRefTag> = 10;

        <org.apache.harmony.luni.internal.reflect.ProxyConstants: int LongTag> = 5;

        <org.apache.harmony.luni.internal.reflect.ProxyConstants: int InterfaceMethodRefTag> = 11;

        <org.apache.harmony.luni.internal.reflect.ProxyConstants: int IntegerTag> = 3;

        <org.apache.harmony.luni.internal.reflect.ProxyConstants: int FloatTag> = 4;

        <org.apache.harmony.luni.internal.reflect.ProxyConstants: int FieldRefTag> = 9;

        <org.apache.harmony.luni.internal.reflect.ProxyConstants: int DoubleTag> = 6;

        <org.apache.harmony.luni.internal.reflect.ProxyConstants: int ClassTag> = 7;

        <org.apache.harmony.luni.internal.reflect.ProxyConstants: int AccSuper> = 32;

        <org.apache.harmony.luni.internal.reflect.ProxyConstants: int AccStatic> = 8;

        <org.apache.harmony.luni.internal.reflect.ProxyConstants: int AccPublic> = 1;

        <org.apache.harmony.luni.internal.reflect.ProxyConstants: int AccProtected> = 4;

        <org.apache.harmony.luni.internal.reflect.ProxyConstants: int AccPrivate> = 2;

        <org.apache.harmony.luni.internal.reflect.ProxyConstants: int AccFinal> = 16;

        $r0 = newarray (char)[4];

        $r0[0] = 67;

        $r0[1] = 111;

        $r0[2] = 100;

        $r0[3] = 101;

        <org.apache.harmony.luni.internal.reflect.ProxyConstants: char[] CodeName> = $r0;

        $r0 = newarray (char)[10];

        $r0[0] = 69;

        $r0[1] = 120;

        $r0[2] = 99;

        $r0[3] = 101;

        $r0[4] = 112;

        $r0[5] = 116;

        $r0[6] = 105;

        $r0[7] = 111;

        $r0[8] = 110;

        $r0[9] = 115;

        <org.apache.harmony.luni.internal.reflect.ProxyConstants: char[] ExceptionsName> = $r0;

        $r0 = newarray (char)[6];

        $r0[0] = 60;

        $r0[1] = 105;

        $r0[2] = 110;

        $r0[3] = 105;

        $r0[4] = 116;

        $r0[5] = 62;

        <org.apache.harmony.luni.internal.reflect.ProxyConstants: char[] Init> = $r0;

        return;
    }
}
